rb/BotMethods.py
rb/ChannelMethods.py
rb/GroupMethods.py
rb/UserMethods.py
rb/__init__.py
rb/connection.py
rb/methods.py
rb/parser.py
rb/rubino.py
rb/sessions.py
rb/websocket.py
rb/clients/__init__.py
rb/clients/clients.py
rb/crypto/__init__.py
rb/crypto/crypto.py
rb/events/__init__.py
rb/events/events.py
rb/exceptions/__init__.py
rb/exceptions/errors.py
rb/extensions/__init__.py
rb/extensions/installer.py
rb/extensions/tools.py
rb/models/__init__.py
rb/models/models.py
rb/responses/__init__.py
rb/responses/respond_models.py
rb/storage/__init__.py
rb/storage/storage.py
rubx-10.6.9.dist-info/METADATA
rubx-10.6.9.dist-info/WHEEL
rubx-10.6.9.dist-info/top_level.txt
rubx-10.6.9.dist-info/RECORD
