Metadata-Version: 2.1
Name: rubx
Version: 10.6.9
Summary: Iranian rubx library - rubika client module
Home-page: https://github.com/mester-root/rubx
Download-URL: https://github.com/mester-root/rubx/releases/latest
Author: Saleh
Author-email: m3st3r.r00t@gmail.com
License: MIT
Project-URL: Tracker, https://github.com/mester-root/rubx/issues
Project-URL: Channel, https://t.me/rubx_library
Project-URL: Source, https://github.com/mester-root/rubx
Project-URL: Documentation, https://github.com/Mester-Root/rubx/blob/main/README.md
Keywords: messenger,python,self,rubx,rubix,rubikax,rubika,bot,robot,library,rubikalib,rubikalibrary,rubika.ir,web.rubika.ir,telegram
Classifier: Development Status :: 5 - Production/Stable
Classifier: Intended Audience :: Developers
Classifier: Natural Language :: English
Classifier: License :: OSI Approved :: GNU Lesser General Public License v3 (LGPLv3)
Classifier: Operating System :: OS Independent
Classifier: Programming Language :: Python
Classifier: Programming Language :: Python :: 3
Classifier: Programming Language :: Python :: 3.5
Classifier: Programming Language :: Python :: 3.6
Classifier: Programming Language :: Python :: 3.7
Classifier: Programming Language :: Python :: 3.8
Classifier: Programming Language :: Python :: 3.9
Classifier: Programming Language :: Python :: 3.10
Classifier: Programming Language :: Python :: 3.11
Classifier: Programming Language :: Python :: Implementation
Classifier: Programming Language :: Python :: Implementation :: CPython
Classifier: Programming Language :: Python :: Implementation :: PyPy
Classifier: Topic :: Internet
Classifier: Topic :: Communications
Classifier: Topic :: Communications :: Chat
Classifier: Topic :: Software Development :: Libraries
Classifier: Topic :: Software Development :: Libraries :: Python Modules
Classifier: Topic :: Software Development :: Libraries :: Application Frameworks
Requires-Python: ~=3.9
Requires-Dist: requests
Requires-Dist: urllib3
Requires-Dist: datetime
